setup.py
distributions_vc623/Binomialdistribution.py
distributions_vc623/Gaussiandistribution.py
distributions_vc623/Generaldistribution.py
distributions_vc623/__init__.py
distributions_vc623.egg-info/PKG-INFO
distributions_vc623.egg-info/SOURCES.txt
distributions_vc623.egg-info/dependency_links.txt
distributions_vc623.egg-info/not-zip-safe
distributions_vc623.egg-info/top_level.txt