Metadata-Version: 2.1
Name: distributions-vc623
Version: 0.1
Summary: Gaussian and Binomial distributions
Home-page: UNKNOWN
Author: Victor Chen
Author-email: victor.chen623@gmail.com
License: UNKNOWN
Platform: UNKNOWN
